certbot_dns_metaname/__init__.py
certbot_dns_metaname/dns_metaname.py
certbot_dns_metaname/dns_metaname_test.py
certbot_dns_metaname/metaname.py
certbot_dns_metaname-0.2.5.dist-info/LICENSE.txt
certbot_dns_metaname-0.2.5.dist-info/METADATA
certbot_dns_metaname-0.2.5.dist-info/WHEEL
certbot_dns_metaname-0.2.5.dist-info/entry_points.txt
certbot_dns_metaname-0.2.5.dist-info/top_level.txt
certbot_dns_metaname-0.2.5.dist-info/RECORD
